timor_locations/__init__.py
timor_locations/admin.py
timor_locations/api.py
timor_locations/gis_functions.py
timor_locations/management/__init__.py
timor_locations/management/commands/__init__.py
timor_locations/management/commands/create_topology.py
timor_locations/management/commands/import_timor_geo_data.py
timor_locations/management/commands/import_timor_geo_data_2022.py
timor_locations/management/commands/suco_to_topology.sql
timor_locations/management/commands/timor_topology.py
timor_locations/management/commands/topology_to_topojson.py
timor_locations/migrations/0001_initial.py
timor_locations/migrations/0002_remove_administrativepost_id_remove_municipality_id_and_more.py
timor_locations/migrations/0003_alter_administrativepost_municipality_and_more.py
timor_locations/migrations/0004_alter_administrativepost_date_modified_and_more.py
timor_locations/migrations/0005_topojson.py
timor_locations/migrations/0006_timortopology_edgemap.py
timor_locations/migrations/0007_aldeia_delete_edgemap_delete_timortopology.py
timor_locations/migrations/__init__.py
timor_locations/models.py
timor_locations/router.py
timor_locations/schemas.py
timor_locations/settings.py
timor_locations/urls.py
timor_locations/wsgi.py
timor_locations-0.0.8.dist-info/METADATA
timor_locations-0.0.8.dist-info/WHEEL
timor_locations-0.0.8.dist-info/RECORD
