Metadata-Version: 2.1
Name: timor-locations
Version: 0.0.8
Summary: Timor-Leste geographic datasets
Home-page: https://github.com/catalpainternational/timor_locations
License: GPLv3
Author: Joshua Brooks
Author-email: josh@catalpa.io
Requires-Python: >=3.10,<4.0
Classifier: License :: Other/Proprietary License
Classifier: Programming Language :: Python :: 3
Classifier: Programming Language :: Python :: 3.10
Classifier: Programming Language :: Python :: 3.11
Requires-Dist: django-ninja (>=0.21.0)
Requires-Dist: geojson-pydantic (>=0.6.2,<0.7.0)
Requires-Dist: pydantic (>1.10.6,<2)
Project-URL: Repository, https://github.com/catalpainternational/timor_locations
